MANIFEST.in
Readme.md
setup.py
djkeeper/__init__.py
djkeeper/admin.py
djkeeper/manager.py
djkeeper/models.py
djkeeper/tests.py
djkeeper/views.py
djkeeper.egg-info/PKG-INFO
djkeeper.egg-info/SOURCES.txt
djkeeper.egg-info/dependency_links.txt
djkeeper.egg-info/requires.txt
djkeeper.egg-info/top_level.txt
djkeeper/templates/djkeeper/index.html