Metadata-Version: 1.0
Name: djkeeper
Version: 0.2.4
Summary: Utilities for using ZooKeeper from a Django project.
Home-page: http://github.com/nkvoll/djkeeper
Author: Njal Karevoll
Author-email: njal@karevoll.no
License: MIT
Keywords: zookeeper,pykeeper
Platform: UNKNOWN
Classifier: Development Status :: 4 - Beta
Classifier: License :: OSI Approved :: MIT License
Classifier: Intended Audience :: Developers
Classifier: Intended Audience :: System Administrators
Classifier: Programming Language :: Python :: 2.6
Classifier: Programming Language :: Python :: 2.7
Classifier: Framework :: Django
